python_deploy_test/__init__.py
python_deploy_test/person.py
test/__init__.py
test/test_person.py
python_deploy_test-1.0a0.dist-info/METADATA
python_deploy_test-1.0a0.dist-info/WHEEL
python_deploy_test-1.0a0.dist-info/top_level.txt
python_deploy_test-1.0a0.dist-info/RECORD
